Metadata-Version: 2.1
Name: Orange3-Timeseries
Version: 0.6.3
Summary: Orange3 add-on for exploring time series and sequential data.
Home-page: https://github.com/biolab/orange3-timeseries
Author: Bioinformatics Laboratory, FRI UL
Author-email: info@biolab.si
License: GPLv3+
Keywords: time series,sequence analysis,orange3 add-on,ARIMA,VAR model,forecast
Classifier: Development Status :: 4 - Beta
Classifier: Environment :: X11 Applications :: Qt
Classifier: Environment :: Plugins
Classifier: Programming Language :: Python
Classifier: License :: OSI Approved :: GNU General Public License v3 or later (GPLv3+)
Classifier: Operating System :: OS Independent
Classifier: Topic :: Scientific/Engineering :: Artificial Intelligence
Classifier: Topic :: Scientific/Engineering :: Visualization
Classifier: Topic :: Software Development :: Libraries :: Python Modules
Classifier: Intended Audience :: Education
Classifier: Intended Audience :: Science/Research
Classifier: Intended Audience :: Developers
License-File: LICENSE
Requires-Dist: Orange3 >=3.33.0
Requires-Dist: statsmodels >=0.13.0
Requires-Dist: python-dateutil
Requires-Dist: pandas
Requires-Dist: pandas-datareader
Requires-Dist: numpy
Requires-Dist: scipy >=1.9.2
Requires-Dist: more-itertools
Requires-Dist: yfinance
Requires-Dist: pyqtgraph >=0.13.1
Provides-Extra: doc
Requires-Dist: sphinx ; extra == 'doc'
Requires-Dist: recommonmark ; extra == 'doc'
Requires-Dist: sphinx-rtd-theme ; extra == 'doc'
Provides-Extra: test
Requires-Dist: coverage ; extra == 'test'
